lm_detect/__init__.py
lm_detect/perplexity.py
lm_detect/utils.py
lm_detect-0.0.1.dist-info/LICENSE
lm_detect-0.0.1.dist-info/METADATA
lm_detect-0.0.1.dist-info/WHEEL
lm_detect-0.0.1.dist-info/top_level.txt
lm_detect-0.0.1.dist-info/RECORD
